graph_split/__init__.py
graph_split/split_script.py
graph_split/test.py
graph_split-0.3.2.dist-info/licenses/LICENSE
graph_split-0.3.2.dist-info/METADATA
graph_split-0.3.2.dist-info/WHEEL
graph_split-0.3.2.dist-info/top_level.txt
graph_split-0.3.2.dist-info/RECORD
